MANIFEST.in
ez_setup.py
setup.py
superfcgi/__init__.py
superfcgi/_superfcgi.c
superfcgi/app.py
superfcgi/fork2.py
superfcgi/server.py
superfcgi/superfcgi.py
superfcgi.egg-info/PKG-INFO
superfcgi.egg-info/SOURCES.txt
superfcgi.egg-info/dependency_links.txt
superfcgi.egg-info/entry_points.txt
superfcgi.egg-info/not-zip-safe
superfcgi.egg-info/top_level.txt
superfcgi/management/__init__.py
superfcgi/management/commands/__init__.py
superfcgi/management/commands/runsuperfcgi.py