Metadata-Version: 1.0
Name: superfcgi
Version: 0.1.3
Summary: The only one true way to run WSGI apps through fastcgi
Home-page: UNKNOWN
Author: Victor Kotseruba
Author-email: barbuzaster@gmail.com
License: MIT
Platform: Posix
Platform: MacOS X
Platform: Windows
Classifier: Intended Audience :: Developers
Classifier: License :: OSI Approved :: MIT License
Classifier: Programming Language :: Python
Classifier: Programming Language :: C
Classifier: Topic :: Internet :: WWW/HTTP :: Dynamic Content :: CGI Tools/Libraries
Classifier: Topic :: Software Development :: Libraries :: Python Modules
